access_intake_utils/__init__.py
access_intake_utils/_version.py
access_intake_utils/ard.py
access_intake_utils/util.py
access_intake_utils/chunking/__init__.py
access_intake_utils/chunking/_chunking.py
access_intake_utils-0.1.7.dist-info/licenses/LICENSE
access_intake_utils-0.1.7.dist-info/METADATA
access_intake_utils-0.1.7.dist-info/WHEEL
access_intake_utils-0.1.7.dist-info/top_level.txt
access_intake_utils-0.1.7.dist-info/RECORD
